{
	"minecraft:generic_9x1": "net.minecraft.world.inventory.MenuType",
	"minecraft:generic_9x2": "net.minecraft.world.inventory.MenuType",
	"minecraft:generic_9x3": "net.minecraft.world.inventory.MenuType",
	"minecraft:generic_9x4": "net.minecraft.world.inventory.MenuType",
	"minecraft:generic_9x5": "net.minecraft.world.inventory.MenuType",
	"minecraft:generic_9x6": "net.minecraft.world.inventory.MenuType",
	"minecraft:generic_3x3": "net.minecraft.world.inventory.MenuType",
	"minecraft:anvil": "net.minecraft.world.inventory.MenuType",
	"minecraft:beacon": "net.minecraft.world.inventory.MenuType",
	"minecraft:blast_furnace": "net.minecraft.world.inventory.MenuType",
	"minecraft:brewing_stand": "net.minecraft.world.inventory.MenuType",
	"minecraft:crafting": "net.minecraft.world.inventory.MenuType",
	"minecraft:enchantment": "net.minecraft.world.inventory.MenuType",
	"minecraft:furnace": "net.minecraft.world.inventory.MenuType",
	"minecraft:grindstone": "net.minecraft.world.inventory.MenuType",
	"minecraft:hopper": "net.minecraft.world.inventory.MenuType",
	"minecraft:lectern": "net.minecraft.world.inventory.MenuType",
	"minecraft:loom": "net.minecraft.world.inventory.MenuType",
	"minecraft:merchant": "net.minecraft.world.inventory.MenuType",
	"minecraft:shulker_box": "net.minecraft.world.inventory.MenuType",
	"minecraft:smithing": "net.minecraft.world.inventory.MenuType",
	"minecraft:smoker": "net.minecraft.world.inventory.MenuType",
	"minecraft:cartography_table": "net.minecraft.world.inventory.MenuType",
	"minecraft:stonecutter": "net.minecraft.world.inventory.MenuType",
	"bountifulfares:gristmill_screen_handler": "net.fabricmc.fabric.api.screenhandler.v1.ExtendedScreenHandlerType",
	"alloy_forgery:alloy_forge": "net.minecraft.world.inventory.MenuType",
	"apotheosis:reforging": "net.minecraft.world.inventory.MenuType",
	"apotheosis:salvage": "net.minecraft.world.inventory.MenuType",
	"apotheosis:gem_cutting": "net.minecraft.world.inventory.MenuType",
	"kitchenkarrot:air_compressor": "net.minecraft.world.inventory.MenuType",
	"kitchenkarrot:brewing_barrel": "net.minecraft.world.inventory.MenuType",
	"kitchenkarrot:shaker": "net.minecraft.world.inventory.MenuType",
	"littlelogistics:tug_container": "net.minecraft.world.inventory.MenuType",
	"littlelogistics:energy_tug_container": "net.minecraft.world.inventory.MenuType",
	"littlelogistics:steam_locomotive_container": "net.minecraft.world.inventory.MenuType",
	"littlelogistics:energy_locomotive_container": "net.minecraft.world.inventory.MenuType",
	"littlelogistics:fishing_barge_container": "net.minecraft.world.inventory.MenuType",
	"littlelogistics:tug_route_container": "net.minecraft.world.inventory.MenuType",
	"l2backpack:backpack": "net.minecraft.world.inventory.MenuType",
	"l2backpack:dimensional_storage": "net.minecraft.world.inventory.MenuType",
	"l2backpack:arrow_bag": "net.minecraft.world.inventory.MenuType",
	"l2backpack:tool_bag": "net.minecraft.world.inventory.MenuType",
	"l2backpack:armor_bag": "net.minecraft.world.inventory.MenuType",
	"l2backpack:armor_set": "net.minecraft.world.inventory.MenuType",
	"l2backpack:multi_switch": "net.minecraft.world.inventory.MenuType",
	"l2backpack:ender_switch": "net.minecraft.world.inventory.MenuType",
	"toms_storage:ts.storage_terminal.container": "net.minecraft.world.inventory.MenuType",
	"toms_storage:ts.crafting_terminal.container": "net.minecraft.world.inventory.MenuType",
	"toms_storage:ts.inv_connector_filter.container": "net.minecraft.world.inventory.MenuType",
	"toms_storage:ts.level_emitter.container": "net.minecraft.world.inventory.MenuType",
	"toms_storage:ts.inventory_link.container": "net.minecraft.world.inventory.MenuType",
	"toms_storage:ts.item_filter.container": "net.minecraft.world.inventory.MenuType",
	"toms_storage:ts.tag_item_filter.container": "net.minecraft.world.inventory.MenuType",
	"ironchest:iron_chest": "net.minecraft.world.inventory.MenuType",
	"ironchest:gold_chest": "net.minecraft.world.inventory.MenuType",
	"ironchest:diamond_chest": "net.minecraft.world.inventory.MenuType",
	"ironchest:crystal_chest": "net.minecraft.world.inventory.MenuType",
	"ironchest:copper_chest": "net.minecraft.world.inventory.MenuType",
	"ironchest:obsidian_chest": "net.minecraft.world.inventory.MenuType",
	"ironchest:dirt_chest": "net.minecraft.world.inventory.MenuType",
	"astikorcarts:plow": "net.minecraft.world.inventory.MenuType",
	"piercingpaxels:paxel": "net.minecraft.world.inventory.MenuType",
	"cosmeticarmorreworked:inventorycosarmor": "net.minecraft.world.inventory.MenuType",
	"mm_farming:gui_help_crafter_farm": "net.minecraft.world.inventory.MenuType",
	"mm_farming:gui_help_crafter_farm_2": "net.minecraft.world.inventory.MenuType",
	"mm_farming:gui_help_crafter_farm_3": "net.minecraft.world.inventory.MenuType",
	"mm_farming:gui_help_farm_controller_plant": "net.minecraft.world.inventory.MenuType",
	"mm_farming:gui_help_farm_controller_plantphc": "net.minecraft.world.inventory.MenuType",
	"mm_farming:gui_help_farm_controller_plantphc_2": "net.minecraft.world.inventory.MenuType",
	"mm_farming:gui_help_farm_controller_tree": "net.minecraft.world.inventory.MenuType",
	"mm_farming:gui_main_controller_input": "net.minecraft.world.inventory.MenuType",
	"mm_farming:gui_main_controller_system": "net.minecraft.world.inventory.MenuType",
	"mm_farming:gui_main_crafter_farm": "net.minecraft.world.inventory.MenuType",
	"mm_farming:gui_main_farm_controller_plant": "net.minecraft.world.inventory.MenuType",
	"mm_farming:gui_main_farm_controller_plantphc": "net.minecraft.world.inventory.MenuType",
	"mm_farming:gui_main_farm_controller_tree": "net.minecraft.world.inventory.MenuType",
	"apotheosis:enchanting_table": "net.minecraft.world.inventory.MenuType",
	"apotheosis:library": "net.minecraft.world.inventory.MenuType",
	"apotheosis:fletching": "net.minecraft.world.inventory.MenuType",
	"sophisticatedbackpacks:backpack": "net.minecraft.world.inventory.MenuType",
	"sophisticatedbackpacks:settings": "net.minecraft.world.inventory.MenuType",
	"cataclysm:weapon_fusion": "net.minecraft.world.inventory.MenuType",
	"touhou_little_maid:maid_empty_backpack_container": "net.minecraft.world.inventory.MenuType",
	"touhou_little_maid:maid_small_backpack_container": "net.minecraft.world.inventory.MenuType",
	"touhou_little_maid:maid_middle_backpack_container": "net.minecraft.world.inventory.MenuType",
	"touhou_little_maid:maid_big_backpack_container": "net.minecraft.world.inventory.MenuType",
	"touhou_little_maid:maid_crafting_table_backpack_container": "net.minecraft.world.inventory.MenuType",
	"touhou_little_maid:maid_ender_chest_container": "net.minecraft.world.inventory.MenuType",
	"touhou_little_maid:maid_furnace_container": "net.minecraft.world.inventory.MenuType",
	"touhou_little_maid:maid_tank_container": "net.minecraft.world.inventory.MenuType",
	"touhou_little_maid:maid_config_container": "net.minecraft.world.inventory.MenuType",
	"touhou_little_maid:wireless_io_container": "net.minecraft.world.inventory.MenuType",
	"touhou_little_maid:picnic_basket_container": "net.minecraft.world.inventory.MenuType",
	"mm_grinding:gui_help_grinder_controller_mobrel": "net.minecraft.world.inventory.MenuType",
	"mm_grinding:gui_main_controller_input": "net.minecraft.world.inventory.MenuType",
	"mm_grinding:gui_main_controller_system": "net.minecraft.world.inventory.MenuType",
	"mm_grinding:gui_main_crafter_grinder": "net.minecraft.world.inventory.MenuType",
	"mm_grinding:gui_main_egg_crafter": "net.minecraft.world.inventory.MenuType",
	"mm_grinding:gui_main_grinder_controller_boss_dragon": "net.minecraft.world.inventory.MenuType",
	"mm_grinding:gui_main_grinder_controller_boss_wither": "net.minecraft.world.inventory.MenuType",
	"mm_grinding:gui_main_grinder_controller_mob": "net.minecraft.world.inventory.MenuType",
	"mm_grinding:gui_main_controller_input_2": "net.minecraft.world.inventory.MenuType",
	"mm_grinding:gui_help_crafter_grinder": "net.minecraft.world.inventory.MenuType",
	"mm_grinding:gui_help_crafter_grinder_2": "net.minecraft.world.inventory.MenuType",
	"mm_grinding:gui_help_crafter_grinder_3": "net.minecraft.world.inventory.MenuType",
	"mm_grinding:gui_help_egg_crafter": "net.minecraft.world.inventory.MenuType",
	"mm_grinding:gui_help_egg_crafter_2": "net.minecraft.world.inventory.MenuType",
	"mm_grinding:gui_help_grinder_controller_boss_dragon": "net.minecraft.world.inventory.MenuType",
	"mm_grinding:gui_help_grinder_controller_boss_wither": "net.minecraft.world.inventory.MenuType",
	"mm_grinding:gui_help_grinder_controller_mob": "net.minecraft.world.inventory.MenuType",
	"mm_grinding:gui_help_grinder_controller_mob_2": "net.minecraft.world.inventory.MenuType",
	"mm_grinding:gui_help_grinder_controller_mob_3": "net.minecraft.world.inventory.MenuType",
	"useless_sword:shulker_sword_gui": "net.minecraft.world.inventory.MenuType",
	"useless_sword:dimensional_breacher_gui": "net.minecraft.world.inventory.MenuType",
	"creativecore:container": "team.creative.creativecore.CreativeCore$1",
	"l2hostility:hostility_beacon": "net.minecraft.world.inventory.MenuType",
	"l2hostility:equipments": "net.minecraft.world.inventory.MenuType",
	"l2hostility:curios": "net.minecraft.world.inventory.MenuType",
	"miners_delight:copper_pot": "net.minecraft.world.inventory.MenuType",
	"automobility:auto_mechanic_table": "net.minecraft.world.inventory.MenuType",
	"automobility:single_slot": "net.minecraft.world.inventory.MenuType",
	"drinkbeer:beer_barrel_container": "net.minecraft.world.inventory.MenuType",
	"drinkbeer:trade_box_normal_container": "net.minecraft.world.inventory.MenuType",
	"iter_rpg:mob_placer_gui": "net.minecraft.world.inventory.MenuType",
	"iter_rpg:spellbook_gui": "net.minecraft.world.inventory.MenuType",
	"iter_rpg:grim_locker_gui": "net.minecraft.world.inventory.MenuType",
	"iter_rpg:void_maw_gui": "net.minecraft.world.inventory.MenuType",
	"iter_rpg:arcanist_table_gui": "net.minecraft.world.inventory.MenuType",
	"iter_rpg:elemental_armor_mode_switch_gui": "net.minecraft.world.inventory.MenuType",
	"mm_cooking:gui_help_kitchen": "net.minecraft.world.inventory.MenuType",
	"mm_cooking:gui_help_kitchen_cooking_oven": "net.minecraft.world.inventory.MenuType",
	"mm_cooking:gui_help_kitchen_cutting_board": "net.minecraft.world.inventory.MenuType",
	"mm_cooking:gui_help_kitchen_skillet": "net.minecraft.world.inventory.MenuType",
	"mm_cooking:gui_help_trader_food": "net.minecraft.world.inventory.MenuType",
	"mm_cooking:gui_main_controller_input": "net.minecraft.world.inventory.MenuType",
	"mm_cooking:gui_main_controller_output": "net.minecraft.world.inventory.MenuType",
	"mm_cooking:gui_main_controller_structure": "net.minecraft.world.inventory.MenuType",
	"mm_cooking:gui_main_controller_system": "net.minecraft.world.inventory.MenuType",
	"mm_cooking:gui_main_kitchen": "net.minecraft.world.inventory.MenuType",
	"mm_cooking:gui_main_kitchen_controller": "net.minecraft.world.inventory.MenuType",
	"mm_cooking:gui_main_kitchen_cooking_oven": "net.minecraft.world.inventory.MenuType",
	"mm_cooking:gui_main_kitchen_cutting_board": "net.minecraft.world.inventory.MenuType",
	"mm_cooking:gui_main_kitchen_skillet": "net.minecraft.world.inventory.MenuType",
	"mm_cooking:gui_main_trader_food": "net.minecraft.world.inventory.MenuType",
	"curios:curios_container": "net.minecraft.world.inventory.MenuType",
	"curios:curios_container_v2": "net.minecraft.world.inventory.MenuType",
	"mcwfurnitures:example_chest": "net.minecraft.world.inventory.MenuType",
	"createbigcannons:set_timed_fuze": "net.minecraft.world.inventory.MenuType",
	"createbigcannons:set_proximity_fuze": "net.minecraft.world.inventory.MenuType",
	"createbigcannons:set_delayed_fuze": "net.minecraft.world.inventory.MenuType",
	"createbigcannons:autocannon_ammo_container": "net.minecraft.world.inventory.MenuType",
	"l2tabs:curios": "net.minecraft.world.inventory.MenuType",
	"mm_mining:gui_main_crafter_miner": "net.minecraft.world.inventory.MenuType",
	"mm_mining:gui_main_miner_controller": "net.minecraft.world.inventory.MenuType",
	"mm_mining:gui_main_ore_smelter_controller": "net.minecraft.world.inventory.MenuType",
	"mm_mining:gui_main_controller_system": "net.minecraft.world.inventory.MenuType",
	"mm_mining:gui_main_crusher_controller": "net.minecraft.world.inventory.MenuType",
	"mm_mining:gui_help_crafter_miner": "net.minecraft.world.inventory.MenuType",
	"mm_mining:gui_help_crusher_controller": "net.minecraft.world.inventory.MenuType",
	"mm_mining:gui_help_miner_controller": "net.minecraft.world.inventory.MenuType",
	"mm_mining:gui_help_ore_smelter_controller": "net.minecraft.world.inventory.MenuType",
	"mm_mining:gui_help_crafter_miner_2": "net.minecraft.world.inventory.MenuType",
	"mm_mining:gui_help_crusher_controller_2": "net.minecraft.world.inventory.MenuType",
	"mm_mining:gui_help_crusher_controller_3": "net.minecraft.world.inventory.MenuType",
	"mm_mining:gui_help_miner_controller_2": "net.minecraft.world.inventory.MenuType",
	"mm_mining:gui_help_ore_smelter_controller_2": "net.minecraft.world.inventory.MenuType",
	"mm_mining:gui_main_controller_input": "net.minecraft.world.inventory.MenuType",
	"mm_mining:gui_main_mining_machine_controller_digital": "net.minecraft.world.inventory.MenuType",
	"mm_mining:gui_main_mining_machine_controller_horizontal": "net.minecraft.world.inventory.MenuType",
	"mm_mining:gui_main_mining_machine_controller_tunnel": "net.minecraft.world.inventory.MenuType",
	"mm_mining:gui_main_mining_machine_controller_vertical": "net.minecraft.world.inventory.MenuType",
	"lightmanscurrency:atm": "net.minecraft.world.inventory.MenuType",
	"lightmanscurrency:coinmint": "net.minecraft.world.inventory.MenuType",
	"lightmanscurrency:network_terminal": "net.minecraft.world.inventory.MenuType",
	"lightmanscurrency:trader": "net.minecraft.world.inventory.MenuType",
	"lightmanscurrency:trader_block": "net.minecraft.world.inventory.MenuType",
	"lightmanscurrency:trader_network_all": "net.minecraft.world.inventory.MenuType",
	"lightmanscurrency:slot_machine": "net.minecraft.world.inventory.MenuType",
	"lightmanscurrency:trader_storage": "net.minecraft.world.inventory.MenuType",
	"lightmanscurrency:wallet": "net.minecraft.world.inventory.MenuType",
	"lightmanscurrency:wallet_bank": "net.minecraft.world.inventory.MenuType",
	"lightmanscurrency:ticket_machine": "net.minecraft.world.inventory.MenuType",
	"lightmanscurrency:trader_interface": "net.minecraft.world.inventory.MenuType",
	"lightmanscurrency:trader_recovery": "net.minecraft.world.inventory.MenuType",
	"lightmanscurrency:player_trading": "net.minecraft.world.inventory.MenuType",
	"lightmanscurrency:coin_chest": "net.minecraft.world.inventory.MenuType",
	"lightmanscurrency:tax_collector": "net.minecraft.world.inventory.MenuType",
	"lightmanscurrency:coin_management": "net.minecraft.world.inventory.MenuType",
	"crockpot:crock_pot": "net.minecraft.world.inventory.MenuType",
	"modulargolems:equipments": "net.minecraft.world.inventory.MenuType",
	"modulargolems:config_toggle": "net.minecraft.world.inventory.MenuType",
	"modulargolems:config_pickup": "net.minecraft.world.inventory.MenuType",
	"modulargolems:config_target": "net.minecraft.world.inventory.MenuType",
	"modulargolems:config_path": "net.minecraft.world.inventory.MenuType",
	"modulargolems:golem_curios": "net.minecraft.world.inventory.MenuType",
	"l2artifacts:filtered": "net.minecraft.world.inventory.MenuType",
	"l2artifacts:recycle": "net.minecraft.world.inventory.MenuType",
	"l2artifacts:upgrade": "net.minecraft.world.inventory.MenuType",
	"l2artifacts:dissolve": "net.minecraft.world.inventory.MenuType",
	"l2artifacts:augment": "net.minecraft.world.inventory.MenuType",
	"l2artifacts:shape": "net.minecraft.world.inventory.MenuType",
	"l2artifacts:swap": "net.minecraft.world.inventory.MenuType",
	"lkartifacts:evolve_anvil_menu": "net.minecraft.world.inventory.MenuType",
	"alexsmobs:transmutation_table": "net.minecraft.world.inventory.MenuType",
	"railways:mounted_toolbox": "net.minecraft.world.inventory.MenuType",
	"twilightforest:uncrafting": "net.minecraft.world.inventory.MenuType",
	"farmersdelight:cooking_pot": "net.minecraft.world.inventory.MenuType",
	"enigmaticlegacy:lore_inscriber_container": "net.minecraft.world.inventory.MenuType",
	"vinery:fermentation_barrel_gui_handler": "net.minecraft.world.inventory.MenuType",
	"vinery:apple_press_gui_handler": "net.minecraft.world.inventory.MenuType",
	"vinery:basket_gui_handler": "net.minecraft.world.inventory.MenuType",
	"herbalbrews:tea_kettle_gui_handler": "net.minecraft.world.inventory.MenuType",
	"herbalbrews:cauldron_gui_handler": "net.minecraft.world.inventory.MenuType",
	"bakery:stove_gui_handler": "net.minecraft.world.inventory.MenuType",
	"bakery:cooking_pot_gui_handler": "net.minecraft.world.inventory.MenuType",
	"candlelight:cooking_pan_gui_handler": "net.minecraft.world.inventory.MenuType",
	"candlelight:cooking_pot_gui_handler": "net.minecraft.world.inventory.MenuType",
	"candlelight:letter_screen": "net.minecraft.world.inventory.MenuType",
	"beachparty:tiki_bar_gui_handler": "net.minecraft.world.inventory.MenuType",
	"beachparty:mini_fridge_gui_handler": "net.minecraft.world.inventory.MenuType",
	"silence_s_defense_tower:h_xshengji": "net.minecraft.world.inventory.MenuType",
	"silence_s_defense_tower:wx_zgui": "net.minecraft.world.inventory.MenuType",
	"silence_s_defense_tower:n_dgui": "net.minecraft.world.inventory.MenuType",
	"silence_s_defense_tower:xpdie": "net.minecraft.world.inventory.MenuType",
	"silence_s_defense_tower:xpsuan": "net.minecraft.world.inventory.MenuType",
	"silence_s_defense_tower:xp_dcp_5": "net.minecraft.world.inventory.MenuType",
	"silence_s_defense_tower:xp_sjp": "net.minecraft.world.inventory.MenuType",
	"silence_s_defense_tower:xpsw_0": "net.minecraft.world.inventory.MenuType",
	"silence_s_defense_tower:xp_nu": "net.minecraft.world.inventory.MenuType",
	"silence_s_defense_tower:hp": "net.minecraft.world.inventory.MenuType",
	"silence_s_defense_tower:h_dgui": "net.minecraft.world.inventory.MenuType",
	"silence_s_defense_tower:xp_g_biao": "net.minecraft.world.inventory.MenuType",
	"silence_s_defense_tower:t_2gui": "net.minecraft.world.inventory.MenuType",
	"silence_s_defense_tower:handing": "net.minecraft.world.inventory.MenuType",
	"silence_s_defense_tower:xp_candy": "net.minecraft.world.inventory.MenuType",
	"silence_s_defense_tower:xp_biao": "net.minecraft.world.inventory.MenuType",
	"silence_s_defense_tower:xp_jnp": "net.minecraft.world.inventory.MenuType",
	"silence_s_defense_tower:xp_bxjnp": "net.minecraft.world.inventory.MenuType",
	"silence_s_defense_tower:xp_fireworkgui": "net.minecraft.world.inventory.MenuType",
	"silence_s_defense_tower:zh_pgui": "net.minecraft.world.inventory.MenuType",
	"silence_s_defense_tower:xp_jiqirgui": "net.minecraft.world.inventory.MenuType",
	"silence_s_defense_tower:how_1": "net.minecraft.world.inventory.MenuType",
	"silence_s_defense_tower:how_2": "net.minecraft.world.inventory.MenuType",
	"silence_s_defense_tower:xp_nian": "net.minecraft.world.inventory.MenuType",
	"silence_s_defense_tower:xp_bj": "net.minecraft.world.inventory.MenuType",
	"silence_s_defense_tower:text_s_wgui": "net.minecraft.world.inventory.MenuType",
	"silence_s_defense_tower:t_1gui": "net.minecraft.world.inventory.MenuType",
	"silence_s_defense_tower:a_lab_gui": "net.minecraft.world.inventory.MenuType",
	"silence_s_defense_tower:a_lab_gui_2": "net.minecraft.world.inventory.MenuType",
	"silence_s_defense_tower:armor_gui": "net.minecraft.world.inventory.MenuType",
	"silence_s_defense_tower:armor_gui_2": "net.minecraft.world.inventory.MenuType",
	"silence_s_defense_tower:r_table_gui_2": "net.minecraft.world.inventory.MenuType",
	"silence_s_defense_tower:lab_gui_3": "net.minecraft.world.inventory.MenuType",
	"silence_s_defense_tower:xp_biao_du": "net.minecraft.world.inventory.MenuType",
	"silence_s_defense_tower:r_table_gui": "net.minecraft.world.inventory.MenuType",
	"kubejs:menu": "net.minecraft.world.inventory.MenuType",
	"fishermens_trap:fishtrap_menu": "net.minecraft.world.inventory.MenuType",
	"amendments:lectern_edit": "net.minecraft.world.inventory.MenuType",
	"sophisticatedstorage:storage": "net.minecraft.world.inventory.MenuType",
	"sophisticatedstorage:limited_barrel": "net.minecraft.world.inventory.MenuType",
	"sophisticatedstorage:settings": "net.minecraft.world.inventory.MenuType",
	"sophisticatedstorage:limited_barrel_settings": "net.minecraft.world.inventory.MenuType",
	"itemfilters:inventory_filter": "net.minecraft.world.inventory.MenuType",
	"tacz:gun_smith_table_menu": "net.minecraft.world.inventory.MenuType",
	"create:schematic_table": "net.minecraft.world.inventory.MenuType",
	"create:schematicannon": "net.minecraft.world.inventory.MenuType",
	"create:filter": "net.minecraft.world.inventory.MenuType",
	"create:attribute_filter": "net.minecraft.world.inventory.MenuType",
	"create:crafting_blueprint": "net.minecraft.world.inventory.MenuType",
	"create:linked_controller": "net.minecraft.world.inventory.MenuType",
	"create:toolbox": "net.minecraft.world.inventory.MenuType",
	"create:schedule": "net.minecraft.world.inventory.MenuType",
	"create_central_kitchen:cooking_guide": "net.minecraft.world.inventory.MenuType",
	"create_central_kitchen:miners_cooking_guide": "net.minecraft.world.inventory.MenuType",
	"waystones:waystone_selection": "net.minecraft.world.inventory.MenuType",
	"waystones:sharestone_selection": "net.minecraft.world.inventory.MenuType",
	"waystones:warp_plate": "net.minecraft.world.inventory.MenuType",
	"waystones:waystone_settings": "net.minecraft.world.inventory.MenuType",
	"alexscaves:spelunkery_table_menu": "net.minecraft.world.inventory.MenuType",
	"alexscaves:nuclear_furnace_menu": "net.minecraft.world.inventory.MenuType",
	"weaponmaster:workstation_menu": "net.minecraft.world.inventory.MenuType",
	"quark:backpack": "net.minecraft.world.inventory.MenuType",
	"quark:crafter": "net.minecraft.world.inventory.MenuType",
	"quark:crate": "net.minecraft.world.inventory.MenuType",
	"quark:held_shulker_box": "net.minecraft.world.inventory.MenuType",
	"quark:feeding_trough": "net.minecraft.world.inventory.MenuType",
	"quark:matrix_enchanting": "net.minecraft.world.inventory.MenuType",
	"supplementaries:present": "net.minecraft.world.inventory.MenuType",
	"supplementaries:trapped_present": "net.minecraft.world.inventory.MenuType",
	"supplementaries:notice_board": "net.minecraft.world.inventory.MenuType",
	"supplementaries:sack": "net.minecraft.world.inventory.MenuType",
	"supplementaries:safe": "net.minecraft.world.inventory.MenuType",
	"supplementaries:pulley_block": "net.minecraft.world.inventory.MenuType",
	"supplementaries:cannon": "net.minecraft.world.inventory.MenuType",
	"supplementaries:red_merchant": "net.minecraft.world.inventory.MenuType"
}