{
	"minecraft:crafting_shaped": "net.minecraft.world.item.crafting.ShapedRecipe$Serializer",
	"minecraft:crafting_shapeless": "net.minecraft.world.item.crafting.ShapelessRecipe$Serializer",
	"minecraft:crafting_special_armordye": "net.minecraft.world.item.crafting.SimpleCraftingRecipeSerializer",
	"minecraft:crafting_special_bookcloning": "net.minecraft.world.item.crafting.SimpleCraftingRecipeSerializer",
	"minecraft:crafting_special_mapcloning": "net.minecraft.world.item.crafting.SimpleCraftingRecipeSerializer",
	"minecraft:crafting_special_mapextending": "net.minecraft.world.item.crafting.SimpleCraftingRecipeSerializer",
	"minecraft:crafting_special_firework_rocket": "net.minecraft.world.item.crafting.SimpleCraftingRecipeSerializer",
	"minecraft:crafting_special_firework_star": "net.minecraft.world.item.crafting.SimpleCraftingRecipeSerializer",
	"minecraft:crafting_special_firework_star_fade": "net.minecraft.world.item.crafting.SimpleCraftingRecipeSerializer",
	"minecraft:crafting_special_tippedarrow": "net.minecraft.world.item.crafting.SimpleCraftingRecipeSerializer",
	"minecraft:crafting_special_bannerduplicate": "net.minecraft.world.item.crafting.SimpleCraftingRecipeSerializer",
	"minecraft:crafting_special_shielddecoration": "net.minecraft.world.item.crafting.SimpleCraftingRecipeSerializer",
	"minecraft:crafting_special_shulkerboxcoloring": "net.minecraft.world.item.crafting.SimpleCraftingRecipeSerializer",
	"minecraft:crafting_special_suspiciousstew": "net.minecraft.world.item.crafting.SimpleCraftingRecipeSerializer",
	"minecraft:crafting_special_repairitem": "net.minecraft.world.item.crafting.SimpleCraftingRecipeSerializer",
	"minecraft:smelting": "net.minecraft.world.item.crafting.SimpleCookingSerializer",
	"minecraft:blasting": "net.minecraft.world.item.crafting.SimpleCookingSerializer",
	"minecraft:smoking": "net.minecraft.world.item.crafting.SimpleCookingSerializer",
	"minecraft:campfire_cooking": "net.minecraft.world.item.crafting.SimpleCookingSerializer",
	"minecraft:stonecutting": "net.minecraft.world.item.crafting.SingleItemRecipe$Serializer",
	"minecraft:smithing_transform": "net.minecraft.world.item.crafting.SmithingTransformRecipe$Serializer",
	"minecraft:smithing_trim": "net.minecraft.world.item.crafting.SmithingTrimRecipe$Serializer",
	"minecraft:crafting_decorated_pot": "net.minecraft.world.item.crafting.SimpleCraftingRecipeSerializer",
	"bountifulfares:milling": "net.hecco.bountifulfares.recipe.MillingRecipe$Serializer",
	"alloy_forgery:forging": "wraith.alloyforgery.recipe.AlloyForgeRecipeSerializer",
	"prefabricated:condition_crafting_shaped": "com.theomenden.prefabricated.recipe.ConditionedShapedRecipe$Serializer",
	"prefabricated:condition_crafting_shapeless": "com.theomenden.prefabricated.recipe.ConditionedShaplessRecipe$Serializer",
	"prefabricated:condition_smelting": "com.theomenden.prefabricated.recipe.ConditionedSmeltingRecipe$Serializer",
	"mythicmetals:runite_tipped_arrow_recipe": "net.minecraft.world.item.crafting.SimpleCraftingRecipeSerializer",
	"mythicmetals:fold_midas_sword": "nourl.mythicmetals.recipe.MidasFoldingRecipe$Serializer",
	"mythicmetals:tidesinger_smithing_transform": "nourl.mythicmetals.recipe.TidesingerCoralRecipe$Serializer",
	"slashblade:shaped_blade": "mods.flammpfeil.slashblade.recipe.SlashBladeShapedRecipeSerializer",
	"gateways:gate_recipe": "dev.shadowsoffire.gateways.recipe.GatewayRecipeSerializer",
	"paraglider:cosmetic": "tictim.paraglider.contents.recipe.CosmeticRecipe$Serializer",
	"paraglider:statue_bargain": "tictim.paraglider.contents.recipe.SimpleBargainSerializer$Simple",
	"kitchenkarrot:cocktail": "io.github.tt432.kitchenkarrot.recipes.base.BaseSerializer",
	"kitchenkarrot:air_compressing": "io.github.tt432.kitchenkarrot.recipes.base.BaseSerializer",
	"kitchenkarrot:brewing_barrel": "io.github.tt432.kitchenkarrot.recipes.base.BaseSerializer",
	"kitchenkarrot:plate": "io.github.tt432.kitchenkarrot.recipes.base.BaseSerializer",
	"tombstone:disableable_shapeless": "ovh.corail.tombstone.recipe.ShapelessSerializer",
	"tombstone:disableable_shaped": "ovh.corail.tombstone.recipe.ShapedSerializer",
	"tombstone:enchanted_grave_key": "ovh.corail.tombstone.recipe.ShapelessSerializer",
	"tombstone:familiar_receptacle": "ovh.corail.tombstone.recipe.ShapedSerializer",
	"littlelogistics:tug_route_copy": "net.minecraft.world.item.crafting.SimpleCraftingRecipeSerializer",
	"littlelogistics:loco_route_copy": "net.minecraft.world.item.crafting.SimpleCraftingRecipeSerializer",
	"chimes:crafting_wind_bell_custom": "net.minecraft.world.item.crafting.SimpleCraftingRecipeSerializer",
	"l2backpack:backpack_dye": "dev.xkmc.l2library.serial.recipe.AbstractShapelessRecipe$Serializer",
	"l2backpack:backpack_upgrade": "dev.xkmc.l2library.serial.recipe.AbstractSmithingRecipe$Serializer",
	"l2backpack:drawer_upgrade": "dev.xkmc.l2library.serial.recipe.AbstractSmithingRecipe$Serializer",
	"l2backpack:multiswitch_craft": "dev.xkmc.l2library.serial.recipe.AbstractShapedRecipe$Serializer",
	"colytra:elytra_attachment": "net.minecraft.world.item.crafting.SimpleCraftingRecipeSerializer",
	"colytra:elytra_detachment": "net.minecraft.world.item.crafting.SimpleCraftingRecipeSerializer",
	"fruitsdelight:jelly_craft_shapeless": "dev.xkmc.l2library.serial.recipe.AbstractShapelessRecipe$Serializer",
	"fruitsdelight:jelly_craft_shaped": "dev.xkmc.l2library.serial.recipe.AbstractShapedRecipe$Serializer",
	"sophisticatedcore:upgrade_next_tier": "net.p3pp3rf1y.sophisticatedcore.crafting.UpgradeNextTierRecipe$Serializer",
	"sophisticatedcore:upgrade_clear": "net.minecraft.world.item.crafting.SimpleCraftingRecipeSerializer",
	"apotheosis:enchanting": "dev.shadowsoffire.apotheosis.ench.table.EnchantingRecipe$Serializer",
	"apotheosis:keep_nbt_enchanting": "dev.shadowsoffire.apotheosis.ench.table.KeepNBTEnchantingRecipe$Serializer",
	"apotheosis:spawner_modifier": "dev.shadowsoffire.apotheosis.spawn.modifiers.SpawnerModifier$Serializer",
	"apotheosis:socketing": "dev.shadowsoffire.apotheosis.adventure.affix.socket.SocketingRecipe$Serializer",
	"apotheosis:expulsion": "dev.shadowsoffire.apotheosis.adventure.affix.socket.ExpulsionRecipe$Serializer",
	"apotheosis:extraction": "dev.shadowsoffire.apotheosis.adventure.affix.socket.ExtractionRecipe$Serializer",
	"apotheosis:unnaming": "dev.shadowsoffire.apotheosis.adventure.affix.socket.UnnamingRecipe$Serializer",
	"apotheosis:add_sockets": "dev.shadowsoffire.apotheosis.adventure.affix.socket.AddSocketsRecipe$Serializer",
	"apotheosis:salvaging": "dev.shadowsoffire.apotheosis.adventure.affix.salvaging.SalvagingRecipe$Serializer",
	"apotheosis:reforging": "dev.shadowsoffire.apotheosis.adventure.affix.reforging.ReforgingRecipe$Serializer",
	"apotheosis:potion_charm": "dev.shadowsoffire.apotheosis.potion.PotionCharmRecipe$Serializer",
	"apotheosis:potion_charm_enchanting": "dev.shadowsoffire.apotheosis.potion.PotionEnchantingRecipe$Serializer",
	"apotheosis:fletching": "dev.shadowsoffire.apotheosis.village.fletching.FletchingRecipe$Serializer",
	"bookshelf:shaped_durability": "net.darkhax.bookshelf.impl.data.recipes.crafting.ShapedDurabilityRecipe$Serializer",
	"bookshelf:shapeless_durability": "net.darkhax.bookshelf.impl.data.recipes.crafting.ShapelessDurabilityRecipe$Serializer",
	"sophisticatedbackpacks:backpack_dye": "net.minecraft.world.item.crafting.SimpleCraftingRecipeSerializer",
	"sophisticatedbackpacks:backpack_upgrade": "net.p3pp3rf1y.sophisticatedbackpacks.crafting.BackpackUpgradeRecipe$Serializer",
	"sophisticatedbackpacks:smithing_backpack_upgrade": "net.p3pp3rf1y.sophisticatedbackpacks.crafting.SmithingBackpackUpgradeRecipe$Serializer",
	"sophisticatedbackpacks:basic_backpack": "net.p3pp3rf1y.sophisticatedbackpacks.crafting.BasicBackpackRecipe$Serializer",
	"cataclysm:weapon_fusion": "com.github.L_Ender.cataclysm.crafting.WeaponfusionRecipe$Serializer",
	"cataclysm:amethyst_bless": "com.github.L_Ender.cataclysm.crafting.AltarOfAmethystRecipe$Serializer",
	"touhou_little_maid:altar_crafting": "com.github.tartaricacid.touhoulittlemaid.crafting.AltarRecipeSerializer",
	"twilightdelight:frozen": "dev.xkmc.l2library.serial.recipe.BaseRecipe$RecType",
	"l2complements:burnt": "dev.xkmc.l2library.serial.recipe.BaseRecipe$RecType",
	"l2complements:diffusion": "dev.xkmc.l2library.serial.recipe.BaseRecipe$RecType",
	"spartanshields:apply_banner": "com.oblivioussp.spartanshields.item.crafting.ShieldBannerRecipe$Serializer",
	"spartanshields:upgrade_powered_shield": "com.oblivioussp.spartanshields.item.crafting.PoweredShieldUpgradeRecipe$Serializer",
	"automobility:auto_mechanic_table": "io.github.foundationgames.automobility.recipe.AutoMechanicTableRecipeSerializer",
	"drinkbeer:brewing": "lekavar.lma.drinkbeer.recipes.BrewingRecipe$Serializer",
	"createbigcannons:melting": "com.simibubi.create.content.processing.recipe.ProcessingRecipeSerializer",
	"createbigcannons:munition_fuzing": "rbasamoyai.createbigcannons.index.CBCRecipeTypes$SimpleRecipeSerializer",
	"createbigcannons:cartridge_assembly": "rbasamoyai.createbigcannons.index.CBCRecipeTypes$SimpleRecipeSerializer",
	"createbigcannons:big_cartridge_filling": "rbasamoyai.createbigcannons.index.CBCRecipeTypes$SimpleRecipeSerializer",
	"createbigcannons:big_cartridge_filling_deployer": "rbasamoyai.createbigcannons.index.CBCRecipeTypes$SimpleRecipeSerializer",
	"createbigcannons:munition_fuzing_deployer": "rbasamoyai.createbigcannons.index.CBCRecipeTypes$SimpleRecipeSerializer",
	"createbigcannons:cartridge_assembly_deployer": "rbasamoyai.createbigcannons.index.CBCRecipeTypes$SimpleRecipeSerializer",
	"createbigcannons:tracer_application": "rbasamoyai.createbigcannons.index.CBCRecipeTypes$SimpleRecipeSerializer",
	"createbigcannons:tracer_application_deployer": "rbasamoyai.createbigcannons.index.CBCRecipeTypes$SimpleRecipeSerializer",
	"createbigcannons:autocannon_ammo_container_filling_deployer": "rbasamoyai.createbigcannons.index.CBCRecipeTypes$SimpleRecipeSerializer",
	"createbigcannons:fuze_removal": "rbasamoyai.createbigcannons.index.CBCRecipeTypes$SimpleRecipeSerializer",
	"createbigcannons:tracer_removal": "rbasamoyai.createbigcannons.index.CBCRecipeTypes$SimpleRecipeSerializer",
	"barbequesdelight:grilling": "dev.xkmc.l2library.serial.recipe.BaseRecipe$RecType",
	"barbequesdelight:skewering": "dev.xkmc.l2library.serial.recipe.BaseRecipe$RecType",
	"barbequesdelight:combine": "dev.xkmc.l2library.serial.recipe.AbstractShapelessRecipe$Serializer",
	"lightmanscurrency:crafting_wallet_upgrade": "io.github.lightman314.lightmanscurrency.common.crafting.WalletUpgradeRecipe$Serializer",
	"lightmanscurrency:coin_mint": "io.github.lightman314.lightmanscurrency.common.crafting.CoinMintRecipe$Serializer",
	"lightmanscurrency:ticket": "io.github.lightman314.lightmanscurrency.common.crafting.TicketRecipe$Serializer",
	"lightmanscurrency:ticket_master": "io.github.lightman314.lightmanscurrency.common.crafting.MasterTicketRecipe$Serializer",
	"crockpot:crock_pot_cooking": "com.sihenzhang.crockpot.recipe.cooking.CrockPotCookingRecipe$Serializer",
	"crockpot:explosion_crafting": "com.sihenzhang.crockpot.recipe.ExplosionCraftingRecipe$Serializer",
	"crockpot:food_values": "com.sihenzhang.crockpot.recipe.FoodValuesDefinition$Serializer",
	"crockpot:parrot_feeding": "com.sihenzhang.crockpot.recipe.ParrotFeedingRecipe$Serializer",
	"crockpot:piglin_bartering": "com.sihenzhang.crockpot.recipe.PiglinBarteringRecipe$Serializer",
	"forge:conditional": "net.minecraftforge.common.crafting.ConditionalRecipe$Serializer",
	"modulargolems:golem_assemble": "dev.xkmc.l2library.serial.recipe.AbstractShapedRecipe$Serializer",
	"zeta:dye_item": "net.minecraft.world.item.crafting.SimpleCraftingRecipeSerializer",
	"lkartifacts:evolve_anvil": "net.matsulen.lkartifacts.recipe.EvolveAnvilRecipe$Serializer",
	"everyxhotpot:crafting_special_hotpot_spice_pack": "net.minecraft.world.item.crafting.SimpleCraftingRecipeSerializer",
	"l2archery:bow_craft": "dev.xkmc.l2library.serial.recipe.AbstractShapedRecipe$Serializer",
	"alexsmobs:mimicream_repair": "net.minecraft.world.item.crafting.SimpleCraftingRecipeSerializer",
	"alexsmobs:bison_upgrade": "net.minecraft.world.item.crafting.SimpleCraftingRecipeSerializer",
	"twilightforest:magic_map_cloning_recipe": "net.minecraft.world.item.crafting.SimpleCraftingRecipeSerializer",
	"twilightforest:maze_map_cloning_recipe": "net.minecraft.world.item.crafting.SimpleCraftingRecipeSerializer",
	"twilightforest:moonworm_queen_repair_recipe": "net.minecraft.world.item.crafting.SimpleCraftingRecipeSerializer",
	"twilightforest:uncrafting": "twilightforest.item.recipe.UncraftingRecipe$Serializer",
	"twilightforest:crumble_horn": "twilightforest.item.recipe.CrumbleRecipe$Serializer",
	"twilightforest:transformation_powder": "twilightforest.item.recipe.TransformPowderRecipe$Serializer",
	"farmersdelight:cooking": "vectorwing.farmersdelight.common.crafting.CookingPotRecipe$Serializer",
	"farmersdelight:cutting": "vectorwing.farmersdelight.common.crafting.CuttingBoardRecipe$Serializer",
	"farmersdelight:food_serving": "net.minecraft.world.item.crafting.SimpleCraftingRecipeSerializer",
	"casualness_delight:deep_frying": "com.va11halla.casualness_delight.recipe.DeepFryingRecipe$Serializer",
	"cuisinedelight:plate_cuisine": "dev.xkmc.l2library.serial.recipe.BaseRecipe$RecType",
	"patchouli:shaped_book_recipe": "vazkii.patchouli.common.recipe.BookRecipeSerializer",
	"patchouli:shapeless_book_recipe": "vazkii.patchouli.common.recipe.BookRecipeSerializer",
	"enigmaticlegacy:mending_mixture_repair": "net.minecraft.world.item.crafting.SimpleCraftingRecipeSerializer",
	"enigmaticlegacy:enchantment_transposing": "net.minecraft.world.item.crafting.SimpleCraftingRecipeSerializer",
	"enigmaticlegacy:void_stone_combine": "net.minecraft.world.item.crafting.SimpleCraftingRecipeSerializer",
	"enigmaticlegacy:bind_to_player": "net.minecraft.world.item.crafting.SimpleCraftingRecipeSerializer",
	"enigmaticlegacy:crafting_shaped_hidden": "net.minecraft.world.item.crafting.SimpleCraftingRecipeSerializer",
	"enigmaticlegacy:shapeless_no_return_craft": "net.minecraft.world.item.crafting.ShapelessRecipe$Serializer",
	"enigmaticlegacy:crafting_shaped_cursed": "com.aizistral.enigmaticlegacy.crafting.CursedShapedRecipe$Serializer",
	"enigmaticlegacy:crafting_shaped_blessed": "com.aizistral.enigmaticlegacy.crafting.BlessedShapedRecipe$Serializer",
	"doapi:conditional": "de.cristelknight.doapi.common.recipe.SimpleConditionalRecipe$Serializer",
	"vinery:wine_fermentation": "net.satisfy.vinery.recipe.FermentationBarrelRecipe$Serializer",
	"vinery:apple_mashing": "net.satisfy.vinery.recipe.ApplePressRecipe$Serializer",
	"herbalbrews:kettle_brewing": "satisfy.herbalbrews.recipe.TeaKettleRecipe$Serializer",
	"herbalbrews:cauldron_brewing": "satisfy.herbalbrews.recipe.CauldronRecipe$Serializer",
	"bakery:pot_cooking": "net.satisfy.bakery.recipe.CookingPotRecipe$Serializer",
	"bakery:stove": "net.satisfy.bakery.recipe.StoveRecipe$Serializer",
	"bakery:crafting_bowl": "net.satisfy.bakery.recipe.CraftingBowlRecipe$Serializer",
	"bakery:baking_station": "net.satisfy.bakery.recipe.BakingStationRecipe$Serializer",
	"brewery:brewing": "net.satisfy.brewery.recipe.BrewingRecipe$Serializer",
	"brewery:drying": "net.satisfy.brewery.recipe.SiloRecipe$Serializer",
	"candlelight:pan_cooking": "net.satisfy.candlelight.recipe.CookingPanRecipe$Serializer",
	"candlelight:pot_cooking": "net.satisfy.candlelight.recipe.CookingPotRecipe$Serializer",
	"beachparty:tiki_bar_mixing": "satisfy.beachparty.recipe.TikiBarRecipe$Serializer",
	"beachparty:mini_fridge_mixing": "satisfy.beachparty.recipe.MiniFridgeRecipe$Serializer",
	"kubejs:shaped": "dev.latvian.mods.kubejs.recipe.special.ShapedKubeJSRecipe$SerializerKJS",
	"kubejs:shapeless": "dev.latvian.mods.kubejs.recipe.special.ShapelessKubeJSRecipe$SerializerKJS",
	"amendments:dye_bottle": "net.minecraft.world.item.crafting.SimpleCraftingRecipeSerializer",
	"sophisticatedstorage:storage_dye": "net.minecraft.world.item.crafting.SimpleCraftingRecipeSerializer",
	"sophisticatedstorage:storage_tier_upgrade": "net.p3pp3rf1y.sophisticatedstorage.crafting.StorageTierUpgradeRecipe$Serializer",
	"sophisticatedstorage:storage_tier_upgrade_shapeless": "net.p3pp3rf1y.sophisticatedstorage.crafting.StorageTierUpgradeShapelessRecipe$Serializer",
	"sophisticatedstorage:shulker_box_from_chest": "net.p3pp3rf1y.sophisticatedstorage.crafting.ShulkerBoxFromChestRecipe$Serializer",
	"sophisticatedstorage:flat_top_barrel_toggle": "net.minecraft.world.item.crafting.SimpleCraftingRecipeSerializer",
	"sophisticatedstorage:barrel_material": "net.minecraft.world.item.crafting.SimpleCraftingRecipeSerializer",
	"tacz:gun_smith_table_crafting": "com.tacz.guns.crafting.GunSmithTableSerializer",
	"create:conversion": "com.simibubi.create.content.processing.recipe.ProcessingRecipeSerializer",
	"create:crushing": "com.simibubi.create.content.processing.recipe.ProcessingRecipeSerializer",
	"create:cutting": "com.simibubi.create.content.processing.recipe.ProcessingRecipeSerializer",
	"create:milling": "com.simibubi.create.content.processing.recipe.ProcessingRecipeSerializer",
	"create:basin": "com.simibubi.create.content.processing.recipe.ProcessingRecipeSerializer",
	"create:mixing": "com.simibubi.create.content.processing.recipe.ProcessingRecipeSerializer",
	"create:compacting": "com.simibubi.create.content.processing.recipe.ProcessingRecipeSerializer",
	"create:pressing": "com.simibubi.create.content.processing.recipe.ProcessingRecipeSerializer",
	"create:sandpaper_polishing": "com.simibubi.create.content.processing.recipe.ProcessingRecipeSerializer",
	"create:splashing": "com.simibubi.create.content.processing.recipe.ProcessingRecipeSerializer",
	"create:haunting": "com.simibubi.create.content.processing.recipe.ProcessingRecipeSerializer",
	"create:deploying": "com.simibubi.create.content.processing.recipe.ProcessingRecipeSerializer",
	"create:filling": "com.simibubi.create.content.processing.recipe.ProcessingRecipeSerializer",
	"create:emptying": "com.simibubi.create.content.processing.recipe.ProcessingRecipeSerializer",
	"create:item_application": "com.simibubi.create.content.processing.recipe.ProcessingRecipeSerializer",
	"create:mechanical_crafting": "com.simibubi.create.content.kinetics.crafter.MechanicalCraftingRecipe$Serializer",
	"create:sequenced_assembly": "com.simibubi.create.content.processing.sequenced.SequencedAssemblyRecipeSerializer",
	"create:toolbox_dyeing": "net.minecraft.world.item.crafting.SimpleCraftingRecipeSerializer",
	"some_assembly_required:sandwich_spouting": "someassemblyrequired.integration.create.recipe.SandwichFluidSpoutingRecipe$Serializer",
	"some_assembly_required:sandwich_potion_spouting": "someassemblyrequired.integration.create.recipe.SandwichPotionSpoutingRecipe$Serializer",
	"create_central_kitchen:cutting_board_deploying": "com.simibubi.create.content.processing.recipe.ProcessingRecipeSerializer",
	"waystones:warp_plate": "net.blay09.mods.waystones.recipe.WarpPlateRecipe$Serializer",
	"alexscaves:cave_map": "net.minecraft.world.item.crafting.SimpleCraftingRecipeSerializer",
	"alexscaves:nuclear_furnace": "net.minecraft.world.item.crafting.SimpleCookingSerializer",
	"skilltree:gem_insertion": "daripher.skilltree.recipe.GemInsertionRecipe$Serializer",
	"skilltree:weapon_poisoning": "daripher.skilltree.recipe.WeaponPoisoningRecipe$Serializer",
	"skilltree:potion_mixing": "daripher.skilltree.recipe.MixtureRecipe$Serializer",
	"skilltree:crafting_shaped": "daripher.skilltree.recipe.ShapedSkillRequiringRecipe$Serializer",
	"skilltree:crafting_shapeless": "daripher.skilltree.recipe.ShapelessSkillRequiringRecipe$Serializer",
	"skilltree:quiver_filling": "daripher.skilltree.recipe.QuiverFillingRecipe$Serializer",
	"skilltree:gem_upgrade": "daripher.skilltree.recipe.GemUpgradeRecipe$Serializer",
	"quark:dye_item": "net.minecraft.world.item.crafting.SimpleCraftingRecipeSerializer",
	"quark:exclusion": "org.violetmoon.quark.base.recipe.ExclusionRecipe$Serializer",
	"quark:smithing_rune": "org.violetmoon.quark.content.tools.recipe.SmithingRuneRecipe$Serializer",
	"quark:elytra_duplication": "net.minecraft.world.item.crafting.SimpleCraftingRecipeSerializer",
	"quark:slab_to_block": "net.minecraft.world.item.crafting.SimpleCraftingRecipeSerializer",
	"quark:mixed_exclusion": "org.violetmoon.quark.content.building.recipe.MixedExclusionRecipe$Serializer",
	"supplementaries:blackboard_duplicate": "net.minecraft.world.item.crafting.SimpleCraftingRecipeSerializer",
	"supplementaries:bamboo_spikes_tipped": "net.minecraft.world.item.crafting.SimpleCraftingRecipeSerializer",
	"supplementaries:rope_arrow_create": "net.minecraft.world.item.crafting.SimpleCraftingRecipeSerializer",
	"supplementaries:rope_arrow_add": "net.minecraft.world.item.crafting.SimpleCraftingRecipeSerializer",
	"supplementaries:bubble_blower_charge": "net.minecraft.world.item.crafting.SimpleCraftingRecipeSerializer",
	"supplementaries:flag_from_banner": "net.minecraft.world.item.crafting.SimpleCraftingRecipeSerializer",
	"supplementaries:weathered_map": "net.minecraft.world.item.crafting.SimpleCraftingRecipeSerializer",
	"supplementaries:antique_book": "net.minecraft.world.item.crafting.SimpleCraftingRecipeSerializer",
	"supplementaries:soap_clearing": "net.minecraft.world.item.crafting.SimpleCraftingRecipeSerializer",
	"supplementaries:present_dye": "net.minecraft.world.item.crafting.SimpleCraftingRecipeSerializer",
	"supplementaries:trapped_present": "net.minecraft.world.item.crafting.SimpleCraftingRecipeSerializer",
	"supplementaries:item_lore": "net.minecraft.world.item.crafting.SimpleCraftingRecipeSerializer"
}